{
    "@class": "com.kony.gen.viz.model.component.KVizButton",
    "DNDConfig": null,
    "__parentReadjusting__": false,
    "_height_": {
        "type": "string",
        "value": "100%"
    },
    "_left_": {
        "type": "string",
        "value": "0dp"
    },
    "_margin_": [
        6,
        6,
        6,
        6
    ],
    "_padding_": [
        27,
        0,
        0,
        0
    ],
    "_skin_": "s8f2a5650c404528ad9d5ce068a7bc45",
    "_text_": "Back",
    "_top_": {
        "type": "string",
        "value": "0dp"
    },
    "_width_": {
        "type": "string",
        "value": "76dp"
    },
    "canUpdateUI": true,
    "containerweight": 100,
    "contentalignment": 4,
    "displaytext": true,
    "focusskin": "s0696c3010af4a22814c5ede15ab175c",
    "id": "headerButtonLeft",
    "ide_onClick": "AS_Button_d0d4c8205f264537b4181ea0f0a13983",
    "info": null,
    "isvisible": true,
    "kuid": "gc4282b6399345ccbbc6c24013e11d45",
    "masterType": 1,
    "name": "kony.ui.Button",
    "onclick": "AS_Button_b17f3e914256493f8ea5269def794556",
    "paddingLocked": false,
    "paddinginpixel": false,
    "parent": "headerContainer25",
    "pf": "frmLocalStore",
    "wType": "Button",
    "zindex": 1
}