{
    "@class": "com.kony.gen.viz.model.component.KVizButton",
    "DNDConfig": null,
    "__parentReadjusting__": false,
    "_height_": {
        "type": "string",
        "value": "50dp"
    },
    "_left_": {
        "type": "string",
        "value": "37dp"
    },
    "_margin_": [
        6,
        6,
        6,
        6
    ],
    "_padding_": [
        0,
        0,
        0,
        0
    ],
    "_render_": true,
    "_skin_": "saac0cc0a3a14cf19611db6eb9ac4601",
    "_text_": "Dictionary view",
    "_top_": {
        "type": "string",
        "value": "12dp"
    },
    "_width_": {
        "type": "string",
        "value": "300dp"
    },
    "android": {
        "render": false
    },
    "canUpdateUI": true,
    "centerx": {
        "type": "string",
        "value": "50%"
    },
    "containerweight": 100,
    "contentalignment": 5,
    "displaytext": true,
    "focusskin": "saac0cc0a3a14cf19611db6eb9ac4601",
    "id": "btnDictnry",
    "ide_onClick": "AS_Button_j77a169eefb84c54a9446600391a4606",
    "info": null,
    "ipad": {
        "render": true
    },
    "iscustomlayout": false,
    "isvisible": true,
    "kuid": "ia80fe6aedb741f1bd1daf67982e03a4",
    "name": "kony.ui.Button",
    "onclick": "AS_Button_c458bdfe4c764915a677422ef838e3c2",
    "parent": "flxBody",
    "pf": "frmSegmentOptions",
    "retaincontentalignment": false,
    "retainflexpositionproperties": false,
    "spaandroidtablet": {
        "render": false
    },
    "spaipad": {
        "render": false
    },
    "spawindowstablet": {
        "render": false
    },
    "wType": "Button",
    "windows8": {
        "render": false
    },
    "zindex": 1
}