{
    "AS_Button_ebaf6fccf4184d04b30baecc7feefcbf": {
        "id": "AS_Button_ebaf6fccf4184d04b30baecc7feefcbf",
        "type": "ACTION_SEQUENCE",
        "params": [{
            "datatype": "collection",
            "name": "eventobject"
        }],
        "contextObj": {
            "name": "frmAnibottomlefttop",
            "type": "forms",
            "platform": null,
            "KUID": "a63a13de82ef4ff5ab2650d4e66e193f"
        },
        "language": "js",
        "actions": [{
            "id": "NAVIGATE_TO_FORM__ide_onClick_ca534646c0bd4f589e6d0d69af51d2a2",
            "type": "NAVIGATE_TO_FORM",
            "formId": "frmAniAnd",
            "formKUID": "j699625c0f894b0d8cb26994a9b62b86",
            "mappings": {},
            "mappingsOrder": [],
            "parentId": "",
            "callbackType": null,
            "enableMappingEditor": true,
            "package": "",
            "navigationObj": "{\n    \"_meta_\": {\n        \"eventName\": \"onClick\",\n        \"widgetId\": \"headerButtonLeft\"\n    }\n}",
            "isCustomInput": false
        }]
    }
}