{
    "AS_Button_d06aa9580833432391f30fefc1df98a7": {
        "id": "AS_Button_d06aa9580833432391f30fefc1df98a7",
        "type": "ACTION_SEQUENCE",
        "params": [{
            "datatype": "collection",
            "name": "eventobject"
        }],
        "contextObj": {
            "name": "frmSegInvertRotaryView",
            "type": "forms",
            "platform": null,
            "KUID": "be07ce75d3a34efdb522e765451a0600"
        },
        "language": "js",
        "actions": [{
            "id": "NAVIGATE_TO_FORM__ide_onClick_f6b17af5383846d7a47fdc013c175385",
            "type": "NAVIGATE_TO_FORM",
            "formId": "frmSegViews",
            "formKUID": "ef83a5b297e24681b3064707189a0f58",
            "mappings": {},
            "mappingsOrder": [],
            "parentId": "",
            "callbackType": null,
            "enableMappingEditor": true,
            "package": "",
            "navigationObj": "{\n    \"_meta_\": {\n        \"eventName\": \"onClick\",\n        \"widgetId\": \"headerButtonLeft\"\n    }\n}",
            "isCustomInput": false
        }]
    }
}