{
    "AS_Button_heae5556410a4f62b340ff9d66bf40ce": {
        "id": "AS_Button_heae5556410a4f62b340ff9d66bf40ce",
        "type": "ACTION_SEQUENCE",
        "params": [{
            "datatype": "collection",
            "name": "eventobject"
        }],
        "contextObj": {
            "name": "frmAniReveal",
            "type": "forms",
            "platform": null,
            "KUID": "h790da45a48c415e9bcf56c8d48ae0a7"
        },
        "language": "js",
        "actions": [{
            "id": "NAVIGATE_TO_FORM__ide_onClick_ae1d7f7aafa743c4b8319df8ecba9af0",
            "type": "NAVIGATE_TO_FORM",
            "formId": "frmAni",
            "formKUID": "a6018da0eb1e490ab79346b4fc258fd4",
            "mappings": {},
            "mappingsOrder": [],
            "parentId": "",
            "callbackType": null,
            "enableMappingEditor": true,
            "package": "",
            "navigationObj": "{\n    \"_meta_\": {\n        \"eventName\": \"onClick\",\n        \"widgetId\": \"headerButtonLeft\"\n    }\n}",
            "isCustomInput": false
        }]
    }
}